spacetimeengine/__init__.py
spacetimeengine/utilities.py
spacetimeengine/src/__init__.py
spacetimeengine/src/solutions.py
spacetimeengine/src/spacetime.py
spacetimeengine/tests/__init__.py
spacetimeengine/tests/test_spacetime.py
spacetimeengine-0.1.11.dist-info/DESCRIPTION.rst
spacetimeengine-0.1.11.dist-info/METADATA
spacetimeengine-0.1.11.dist-info/RECORD
spacetimeengine-0.1.11.dist-info/WHEEL
spacetimeengine-0.1.11.dist-info/dependency_links.txt
spacetimeengine-0.1.11.dist-info/metadata.json
spacetimeengine-0.1.11.dist-info/top_level.txt
