Metadata-Version: 2.0
Name: spacetimeengine
Version: 0.1.11
Summary: A python physics utility which can analyze any given metric solution to the Einstein field equations.
Home-page: https://github.com/spacetimeengineer/spacetimeengine
Author: Michael.C Ryan
Author-email: spacetime.engineer@gmail.com
License: UNKNOWN
Platform: UNKNOWN
Classifier: Programming Language :: Python :: 3
Classifier: License :: OSI Approved :: BSD License
Classifier: Operating System :: OS Independent
Classifier: Programming Language :: Python
Classifier: Topic :: Scientific/Engineering
Classifier: Topic :: Scientific/Engineering :: Mathematics
Classifier: Topic :: Scientific/Engineering :: Physics
Requires-Dist: sympy
